LICENSE
MANIFEST.in
README.rst
buildout.cfg
develop.cfg
pyproject.toml
requirements.txt
setup.py
version.txt
bob/__init__.py
bob.db.iris.egg-info/PKG-INFO
bob.db.iris.egg-info/SOURCES.txt
bob.db.iris.egg-info/dependency_links.txt
bob.db.iris.egg-info/entry_points.txt
bob.db.iris.egg-info/not-zip-safe
bob.db.iris.egg-info/requires.txt
bob.db.iris.egg-info/top_level.txt
bob/db/__init__.py
bob/db/iris/__init__.py
bob/db/iris/driver.py
bob/db/iris/iris.data
bob/db/iris/iris.names
bob/db/iris/test_examples.py
bob/db/iris/test_scripts.py
bob/db/iris/example/__init__.py
bob/db/iris/example/backprop.py
bob/db/iris/example/lda.py
bob/db/iris/example/rprop.py
doc/conf.py
doc/guide.rst
doc/index.rst
doc/py_api.rst
doc/img/favicon.ico
doc/img/logo.png