Metadata-Version: 1.1
Name: bob.db.iris
Version: 2.1.8
Summary: Bob access API for Fisher's Iris Flower Dataset
Home-page: http://gitlab.idiap.ch/bob/bob.db.iris
Author: Andre Anjos
Author-email: andre.anjos@idiap.ch
License: BSD
Platform: UNKNOWN
Classifier: Framework :: Bob
Classifier: Development Status :: 4 - Beta
Classifier: Intended Audience :: Developers
Classifier: License :: OSI Approved :: BSD License
Classifier: Natural Language :: English
Classifier: Programming Language :: Python
Classifier: Programming Language :: Python :: 3
Classifier: Topic :: Software Development :: Libraries :: Python Modules
